{"result":{"content":[{"type":"text","text":"{\n  \"server\": {\n    \"name\": \"appscreen-listing-mcp\",\n    \"version\": \"1.1.0\"\n  },\n  \"scope\": {\n    \"deterministicOnly\": true,\n    \"includesAiGeneration\": false\n  },\n  \"output\": {\n    \"presetDevices\": {\n      \"iphone-6.9\": {\n        \"width\": 1320,\n        \"height\": 2868\n      },\n      \"iphone-6.7\": {\n        \"width\": 1290,\n        \"height\": 2796\n      },\n      \"iphone-6.5\": {\n        \"width\": 1284,\n        \"height\": 2778\n      },\n      \"iphone-5.5\": {\n        \"width\": 1242,\n        \"height\": 2208\n      },\n      \"ipad-12.9\": {\n        \"width\": 2048,\n        \"height\": 2732\n      },\n      \"ipad-11\": {\n        \"width\": 1668,\n        \"height\": 2388\n      },\n      \"android-phone\": {\n        \"width\": 1080,\n        \"height\": 1920\n      },\n      \"android-phone-hd\": {\n        \"width\": 1440,\n        \"height\": 2560\n      },\n      \"android-tablet-7\": {\n        \"width\": 1200,\n        \"height\": 1920\n      },\n      \"android-tablet-10\": {\n        \"width\": 1600,\n        \"height\": 2560\n      }\n    },\n    \"customDeviceSupported\": true,\n    \"outputModes\": [\n      \"mcp-output\",\n      \"app-dir\"\n    ],\n    \"outputPathTemplate\": \"<outputDir>/<device>/<language>/screenshot-<index>.png\"\n  },\n  \"listingSpecContract\": {\n    \"required\": [\n      \"projectName\",\n      \"outputDevices[]\",\n      \"languages[]\",\n      \"screens[]\"\n    ],\n    \"screenFields\": [\n      \"id\",\n      \"images\",\n      \"text? (headline/subheadline maps)\",\n      \"style? (background/screenshot/text)\"\n    ],\n    \"optional\": [\n      \"defaults\",\n      \"allowPartial\",\n      \"outputMode\",\n      \"outputDir\",\n      \"assetsBaseDir\",\n      \"customSize\"\n    ],\n    \"supportedStyles\": {\n      \"screenshot\": [\n        \"scale\",\n        \"x\",\n        \"y\",\n        \"rotation\",\n        \"perspective\",\n        \"cornerRadius\",\n        \"use3D\",\n        \"device3D (iphone/android)\",\n        \"rotation3D\",\n        \"shadow\"\n      ],\n      \"text\": [\n        \"headlineFont\",\n        \"headlineSize\",\n        \"headlineColor\",\n        \"position (top/bottom)\",\n        \"offsetX\",\n        \"offsetY\",\n        \"textRotation\",\n        \"lineHeight\",\n        \"textShadow\",\n        \"textOutline\"\n      ]\n    }\n  },\n  \"automationSurface\": {\n    \"namespace\": \"window.__appscreenAutomation\",\n    \"methods\": [\n      \"getVersion\",\n      \"healthCheck\",\n      \"getScreenshotCount\",\n      \"resetProject\",\n      \"importLocalizedScreenshots\",\n      \"applyListingSpec\",\n      \"applyProjectJson\",\n      \"renderAllPng\",\n      \"renderPngAt\"\n    ]\n  },\n  \"reliability\": {\n    \"timeoutMs\": 120000,\n    \"bootstrapWaitMs\": 120000,\n    \"comboRetries\": 1,\n    \"sessionRecycleAfterCombos\": 4,\n    \"sessionRecycleIsHardLimit\": false\n  },\n  \"tools\": [\n    \"get_capabilities\",\n    \"list_output_presets\",\n    \"validate_listing_spec\",\n    \"dry_run_listing_job\",\n    \"generate_listing_images\",\n    \"render_project_json\",\n    \"diagnose_app_boot\"\n  ],\n  \"exampleSpec\": {\n    \"projectName\": \"Example Listing Job\",\n    \"outputDevices\": [\n      \"iphone-6.9\",\n      \"android-phone\"\n    ],\n    \"languages\": [\n      \"en\",\n      \"de\"\n    ],\n    \"screens\": [\n      {\n        \"id\": \"screen-1\",\n        \"images\": {\n          \"en\": \"fixtures/screen1-en.png\",\n          \"de\": \"fixtures/screen1-de.png\",\n          \"default\": \"fixtures/screen1-en.png\"\n        },\n        \"text\": {\n          \"headline\": {\n            \"en\": \"Track Everything\",\n            \"de\": \"Alles im Blick\"\n          },\n          \"subheadline\": {\n            \"en\": \"Fast and simple\",\n            \"de\": \"Schnell und einfach\"\n          }\n        }\n      }\n    ],\n    \"outputMode\": \"app-dir\",\n    \"outputDir\": \"img/generated-listings\",\n    \"allowPartial\": false\n  }\n}"}]},"jsonrpc":"2.0","id":1}
